[
    {
        "pron": [
            null,
            "Galoshes"
        ],
        "bn": "galoshes",
        "en": "galoshes",
        "bn_syns": [],
        "en_syns": [
            "golosh",
            "arctic",
            "gumshoe",
            "rubber"
        ],
        "sents": []
    },
    {
        "pron": [
            "ˈgaNGˌland",
            "Gangland"
        ],
        "bn": "gangland",
        "en": "gangland",
        "bn_syns": [],
        "en_syns": [
            "organized crime"
        ],
        "sents": [
            "In Melbourne there have been twenty four <b>gangland</b> killings, the last half-dozen amid the general public.",
            "Missing from his home for four days, he was the 17th victim of <b>gangland</b> crime this year."
        ]
    },
    {
        "pron": [
            "ˈgaNGˌplaNGk",
            "Gangplank"
        ],
        "bn": "gangplank",
        "en": "gangplank",
        "bn_syns": [],
        "en_syns": [
            "gangboard",
            "gangway"
        ],
        "sents": [
            "After the massacre the local port was a scene of panic as people, mostly women, desperate to escape, fought their way up the <b>gangplanks</b> carrying their belongings and children onto badly maintained and overloaded ferries.",
            "Passengers descend a <b>gangplank</b> to access two rowboats, and many more appear already to have disembarked."
        ]
    },
    {
        "pron": [
            "ˈgaskit",
            "Gasket"
        ],
        "bn": "gasket",
        "en": "gasket",
        "bn_syns": [
            "একাধিক ধাতুপাতের সংযোগস্থল থেকে যাতে বাষ্প, গ্যাস ইত্যাদি বেরিয়ে না যায় তার জন্য ব্যবহৃত রবার, এসবেস্টস ইত্যাদির পাত বা রিং",
            "গোটানো পাল বমাস্তুলদণ্ডের সঙ্গে বেঁধে রাখবার ছোট দড়ি"
        ],
        "en_syns": [],
        "sents": [
            "In the past, asbestos has been widely used by South African companies to produce a wide range of products, including <b>gaskets</b> , seals, brake linings, roofing sheets, gutters and other building products, waste pipes and flower pots.",
            "Wema has notified Kracor that the gaskets needed for this campaign are in short supply and there may be as much as a one month delay in providing the <b>gaskets</b> ."
        ]
    },
    {
        "pron": [
            "ˈgi(ə)rˌSHift",
            "Gearshift"
        ],
        "bn": "gearshift",
        "en": "gearshift",
        "bn_syns": [
            "গিয়ার শিফট"
        ],
        "en_syns": [
            "shifter",
            "gear lever",
            "gearstick"
        ],
        "sents": [
            "The technology, which eliminates mechanical control connections, including the steering column, <b>gearshift</b> and pedals, provides greater flexibility of seating positions.",
            "The seats, steering wheel and <b>gearshift</b> are wrapped in leather and the instrument cluster is illuminated in purple."
        ]
    },
    {
        "pron": [
            null,
            "Geeky"
        ],
        "bn": "geeky",
        "en": "geeky",
        "bn_syns": [],
        "en_syns": [],
        "sents": []
    },
    {
        "pron": [
            null,
            "Gentrification"
        ],
        "bn": "gentrification",
        "en": "gentrification",
        "bn_syns": [],
        "en_syns": [],
        "sents": []
    },
    {
        "pron": [
            null,
            "Gerrymandering"
        ],
        "bn": "gerrymandering",
        "en": "gerrymandering",
        "bn_syns": [
            "জাল করা"
        ],
        "en_syns": [],
        "sents": []
    },
    {
        "pron": [
            "ˈgetəˌwā",
            "Getaway"
        ],
        "bn": "getaway",
        "en": "getaway",
        "bn_syns": [
            "পাঠাইয়া দেত্তয়া",
            "পাঠাইয়া সরান",
            "পাঠাইয়া দূর করা",
            "পলায়ন করা",
            "মুক্তি পাওয়া",
            "পালিয়ে যাওয়া",
            "নিস্তার পাওয়া"
        ],
        "en_syns": [
            "escape",
            "breakout",
            "bolt for freedom",
            "flight",
            "disappearance",
            "vanishing act"
        ],
        "sents": [
            "Adding a few tropical plants in containers can give you the fragrance and color of an island <b>getaway</b> in the smallest space.",
            "Roaring fires, home-cooked food and breathtaking scenery are only part of a romantic weekend <b>getaway</b> ."
        ]
    },
    {
        "pron": [
            "ˈgivəˌwā",
            "Giveaway"
        ],
        "bn": "giveaway",
        "en": "giveaway",
        "bn_syns": [
            "ছাড়িয়া দেত্তয়া",
            "বিতরণ করা",
            "বাঁটিয়া দেত্তয়া",
            "ফিরিয়ে দেত্তয়া",
            "ফেরৎ দেত্তয়া",
            "দেত্তয়া",
            "বিকান",
            "দান করা সম্পত্তি",
            "অজান্তে প্রকাশ বা ফাঁস করে ফেলা"
        ],
        "en_syns": [
            "game show",
            "unwrap",
            "disclose",
            "let on",
            "bring out",
            "let out",
            "divulge",
            "discover",
            "break",
            "reveal",
            "expose"
        ],
        "sents": [
            "Otherwise, you would always be selling your goods at <b>giveaway</b> prices far below your total production costs.",
            "Sometimes the title is, or should be, a dead <b>giveaway</b> ."
        ]
    },
    {
        "pron": [
            null,
            "Glamorously"
        ],
        "bn": "glamorously",
        "en": "glamorously",
        "bn_syns": [],
        "en_syns": [],
        "sents": []
    },
    {
        "pron": [
            null,
            "Gleaming"
        ],
        "bn": "gleaming",
        "en": "gleaming",
        "bn_syns": [
            "জ্বলা",
            "উজ্জ্বল হত্তয়া",
            "মিট্মিট করা",
            "প্রতিফলিত করা",
            "ঝিক্মিক্ করা",
            "আলো দেত্তয়া"
        ],
        "en_syns": [
            "lambency",
            "glow",
            "gleam",
            "agleam",
            "nitid",
            "shine",
            "glimmer",
            "glint",
            "glitter",
            "shimmer",
            "sparkle",
            "twinkle",
            "flicker",
            "wink",
            "glisten",
            "flash",
            "glister"
        ],
        "sents": []
    },
    {
        "pron": [
            null,
            "Gleefully"
        ],
        "bn": "gleefully",
        "en": "gleefully",
        "bn_syns": [],
        "en_syns": [
            "joyfully",
            "joyously"
        ],
        "sents": []
    },
    {
        "pron": [
            "ˈglitsē",
            "Glitzy"
        ],
        "bn": "glitzy",
        "en": "glitzy",
        "bn_syns": [],
        "en_syns": [],
        "sents": [
            "Optical showrooms have turned snazzy, and their interiors and exteriors <b>glitzy</b> .",
            "All tickets are booked, the <b>glitzy</b> hotel has been booked, and I will be flying up there this Friday, around mid day."
        ]
    },
    {
        "pron": [
            "gläb",
            "Glob"
        ],
        "bn": "glob",
        "en": "glob",
        "bn_syns": [],
        "en_syns": [
            "ball",
            "clod",
            "lump",
            "clump",
            "chunk"
        ],
        "sents": [
            "It suggests a need for consciousness, for mind, for something that is more than just a collection of synapses in a <b>glob</b> of gray-matter.",
            "It is difficult to start writing about something as seemingly insignificant as a few buttery <b>globs</b> of oil paint, but my addiction to those colourful panes runs deep."
        ]
    },
    {
        "pron": [
            "ˈglōbˌträtər",
            "Globetrotter"
        ],
        "bn": "globetrotter",
        "en": "globetrotter",
        "bn_syns": [],
        "en_syns": [],
        "sents": [
            "Never before has he cut such a powerful figure on the world stage, an adrenaline-charging sensation for the <b>globetrotter</b> and an uplifting spectacle for his audience back home.",
            "Traditional divisions might play on the minds of English players, but it should not upset the current bunch of <b>globetrotters</b> ."
        ]
    },
    {
        "pron": [
            null,
            "Gloriously"
        ],
        "bn": "gloriously",
        "en": "gloriously",
        "bn_syns": [],
        "en_syns": [],
        "sents": []
    },
    {
        "pron": [
            null,
            "Glowering"
        ],
        "bn": "glowering",
        "en": "glowering",
        "bn_syns": [
            "একদৃষ্টিতে তাকান",
            "ক্রুদ্ধভাবে তাকান"
        ],
        "en_syns": [
            "dark",
            "moody",
            "dour",
            "glum",
            "morose",
            "sour",
            "sullen",
            "saturnine",
            "scowl",
            "glare",
            "look daggers",
            "frown",
            "lower",
            "give someone a black look",
            "give someone a dirty look"
        ],
        "sents": []
    },
    {
        "pron": [
            null,
            "Glowingly"
        ],
        "bn": "glowingly",
        "en": "glowingly",
        "bn_syns": [],
        "en_syns": [],
        "sents": []
    },
    {
        "pron": [
            null,
            "Glumly"
        ],
        "bn": "glumly",
        "en": "glumly",
        "bn_syns": [],
        "en_syns": [
            "dourly",
            "sullenly"
        ],
        "sents": []
    },
    {
        "pron": [
            "ˈnô-iNG",
            "Gnawing"
        ],
        "bn": "gnawing",
        "en": "gnawing",
        "bn_syns": [
            "চিবান",
            "ক্ষয় করা",
            "যন্ত্রণা দেত্তয়া",
            "কামড়ে খাত্তয়া",
            "বিরক্ত করা",
            "কষ্ট দেত্তয়া",
            "জ্বালাতন করা",
            "বিব্রত করা"
        ],
        "en_syns": [
            "chew",
            "chomp",
            "champ",
            "bite",
            "munch",
            "crunch",
            "nibble"
        ],
        "sents": [
            "They pull fast ones to get legal prescriptions to alleviate the <b>gnawing</b> need for heroin or crack cocaine.",
            "The self-hatred grew into a constant, <b>gnawing</b> pain."
        ]
    },
    {
        "pron": [
            "ˈgōlˌpōst",
            "Goalpost"
        ],
        "bn": "goalpost",
        "en": "goalpost",
        "bn_syns": [
            "গোল"
        ],
        "en_syns": [],
        "sents": [
            "A goal, worth three points, is scored when the sliotar is played by either team over the goalline between the <b>goalposts</b> and under the crossbar.",
            "The same player rocked Carlow with a thunderous shot off the <b>goalpost</b> for a spectacular goal to put Port ahead for the first time after 12 minutes."
        ]
    },
    {
        "pron": [
            "-ˌgo͞ok,ˈgäbəldēˌgo͝ok",
            "Gobbledygook"
        ],
        "bn": "gobbledygook",
        "en": "gobbledygook",
        "bn_syns": [],
        "en_syns": [
            "gibberish",
            "claptrap",
            "nonsense",
            "rubbish",
            "balderdash",
            "blather",
            "garbage",
            "mumbo jumbo",
            "drivel",
            "tripe",
            "hogwash",
            "baloney",
            "bilge",
            "bull",
            "bunk",
            "guff",
            "eyewash",
            "piffle",
            "twaddle",
            "poppycock",
            "phooey",
            "hooey"
        ],
        "sents": [
            "reams of financial <b>gobbledygook</b>"
        ]
    },
    {
        "pron": [
            "gäb",
            "Gobs"
        ],
        "bn": "gobs",
        "en": "gobs",
        "bn_syns": [
            "নাবিক",
            "হাঁ",
            "মুখ",
            "মুখগহ্বর",
            "আঠাল পদার্থের দলা"
        ],
        "en_syns": [
            "cakehole",
            "maw",
            "yap",
            "trap",
            "hole"
        ],
        "sents": [
            "Yes, you've all seen these emails - they are one long run-on <b>gob</b> of text.",
            "With <b>gobs</b> of young companies struggling to stay afloat, many are rushing headlong into hiring experienced execs who can give them the credibility and stability they need in turbulent economic times."
        ]
    },
    {
        "pron": [
            null,
            "Godchildren"
        ],
        "bn": "godchildren",
        "en": "godchildren",
        "bn_syns": [],
        "en_syns": [],
        "sents": []
    },
    {
        "pron": [
            "ˈgädˈdam",
            "Goddamn"
        ],
        "bn": "goddamn",
        "en": "goddamn",
        "bn_syns": [],
        "en_syns": [
            "goddam",
            "blasted",
            "goddamned",
            "damned",
            "blame",
            "damn",
            "blamed",
            "deuced",
            "blessed",
            "infernal",
            "darned"
        ],
        "sents": []
    },
    {
        "pron": [
            null,
            "Goddamned"
        ],
        "bn": "goddamned",
        "en": "goddamned",
        "bn_syns": [],
        "en_syns": [
            "blasted",
            "goddamned",
            "goddam",
            "damned",
            "blame",
            "damn",
            "blamed",
            "deuced",
            "blessed",
            "infernal",
            "darned",
            "goddamn"
        ],
        "sents": []
    },
    {
        "pron": [
            "ˈgädfərˌsākən",
            "Godforsaken"
        ],
        "bn": "godforsaken",
        "en": "godforsaken",
        "bn_syns": [],
        "en_syns": [
            "wretched",
            "miserable",
            "dreary",
            "dismal",
            "depressing",
            "grim",
            "cheerless",
            "bleak",
            "desolate",
            "gloomy",
            "deserted",
            "neglected",
            "isolated",
            "remote",
            "backward"
        ],
        "sents": [
            "We may be in a <b>godforsaken</b> backwater, and this may be a tent, but it is my operations center, and I will have silence.",
            "But if you are an oilfield fitter in some <b>godforsaken</b> Siberian driller camp and your wages aren't being paid, owning a few hundred shares in the refinery is a bit of an abstract concept."
        ]
    },
    {
        "pron": [
            null,
            "Gorgeously"
        ],
        "bn": "gorgeously",
        "en": "gorgeously",
        "bn_syns": [],
        "en_syns": [
            "resplendently",
            "magnificently",
            "splendidly"
        ],
        "sents": []
    },
    {
        "pron": [
            null,
            "Gracefully"
        ],
        "bn": "gracefully",
        "en": "gracefully",
        "bn_syns": [],
        "en_syns": [
            "graciously"
        ],
        "sents": []
    },
    {
        "pron": [
            null,
            "Grad skula"
        ],
        "bn": "grad স্কুল",
        "en": "grad school",
        "bn_syns": [],
        "en_syns": [
            "graduate school"
        ],
        "sents": []
    },
    {
        "pron": [
            "ˈgrādər",
            "Grader"
        ],
        "bn": "grader",
        "en": "grader",
        "bn_syns": [],
        "en_syns": [],
        "sents": [
            "Approximately 20 percent of tenth to twelfth <b>graders</b> do not complete high school.",
            "Most of the <b>graders</b> and excavators manufactured today come with restriction gauges, and every engine manufacturer has a restriction guideline."
        ]
    },
    {
        "pron": [
            null,
            "Grandly"
        ],
        "bn": "grandly",
        "en": "grandly",
        "bn_syns": [],
        "en_syns": [],
        "sents": []
    },
    {
        "pron": [
            "grəˈnōlə",
            "Granola"
        ],
        "bn": "granola",
        "en": "granola",
        "bn_syns": [],
        "en_syns": [],
        "sents": [
            "They still serve breakfast, of course, but it typically consists of fresh fruit, baked goods from local suppliers, and the old standby of <b>granola</b> or cereal.",
            "In a parfait dish or glass, layer fruit, yogurt and <b>granola</b> ."
        ]
    },
    {
        "pron": [
            null,
            "Graphically"
        ],
        "bn": "graphically",
        "en": "graphically",
        "bn_syns": [],
        "en_syns": [],
        "sents": []
    },
    {
        "pron": [
            null,
            "Gratifying"
        ],
        "bn": "gratifying",
        "en": "gratifying",
        "bn_syns": [
            "খুশি করা",
            "সন্তুষ্ট করা",
            "পরিতৃপ্ত করা",
            "তুষ্ট করা",
            "বাসনা চরিতার্থ করা",
            "চরিতার্থ করা",
            "ঘুস দেত্তয়া",
            "বকশী দেত্তয়া",
            "গা জুড়ান"
        ],
        "en_syns": [
            "sweet",
            "please",
            "gladden",
            "make happy",
            "delight",
            "make someone feel good",
            "satisfy",
            "tickle pink",
            "buck up"
        ],
        "sents": []
    },
    {
        "pron": [
            "ˈgripiNG",
            "Gripping"
        ],
        "bn": "gripping",
        "en": "gripping",
        "bn_syns": [
            "প্রভাববিস্তার করা",
            "গ্রাস করা",
            "চাপা",
            "চাপ দেত্তয়া",
            "চেপে রাখা",
            "চেপে ধরা",
            "দৃঢ়মুষ্টিতে ধরা",
            "আঁকড়ান",
            "আঁকড়াইয়া ধরা",
            "আকর্ষণ করা",
            "সম্যক্ অবধারণা করা"
        ],
        "en_syns": [
            "engrossing",
            "enthralling",
            "absorbing",
            "riveting",
            "captivating",
            "spellbinding",
            "bewitching",
            "fascinating",
            "compulsive",
            "compelling",
            "mesmerizing",
            "thrilling",
            "exciting",
            "action-packed",
            "dramatic",
            "stimulating",
            "unputdownable",
            "page-turning",
            "grasp",
            "clutch",
            "hold",
            "clasp",
            "take hold of",
            "clench",
            "grab",
            "seize",
            "cling to",
            "squeeze",
            "press",
            "glom on to"
        ],
        "sents": [
            "The story of every convert to Judaism is a <b>gripping</b> tale of spiritual discovery.",
            "There are too many <b>gripping</b> moments to mention in this documentary."
        ]
    },
    {
        "pron": [
            "ˈgroun(d)ˌswel",
            "Groundswell"
        ],
        "bn": "groundswell",
        "en": "groundswell",
        "bn_syns": [
            "ঝড় বা ভূমিকম্প-জনিত মন্থর সমুদ্রতরঙ্গ"
        ],
        "en_syns": [
            "upsurge",
            "surge",
            "rise",
            "increase",
            "escalation",
            "outbreak",
            "outburst",
            "wave",
            "upwelling"
        ],
        "sents": [
            "Suppose that a <b>groundswell</b> of popular support finally pushes our proposal through Congress in the form of the Deliberation Day Act of 2012.",
            "The union does not oppose the liberalisation of the postal network, but only urges that it takes place more cautiously in order to prevent a <b>groundswell</b> of opposition."
        ]
    },
    {
        "pron": [
            null,
            "Grungy"
        ],
        "bn": "grungy",
        "en": "grungy",
        "bn_syns": [],
        "en_syns": [],
        "sents": []
    },
    {
        "pron": [
            "ˌgwäkəˈmōlē",
            "Guacamole"
        ],
        "bn": "guacamole",
        "en": "guacamole",
        "bn_syns": [],
        "en_syns": [],
        "sents": [
            "Forget all those bastardisations of potato skins that have been deep-fried and smeared in <b>guacamole</b> .",
            "So, smear the wrap or sandwich with <b>guacamole</b> , hummus, coleslaw or tzatziki and add in some salami, tinned tuna or grated farmhouse cheddar."
        ]
    },
    {
        "pron": [
            null,
            "Guardedly"
        ],
        "bn": "guardedly",
        "en": "guardedly",
        "bn_syns": [],
        "en_syns": [
            "cautiously",
            "conservatively"
        ],
        "sents": []
    },
    {
        "pron": [
            null,
            "Guiltily"
        ],
        "bn": "guiltily",
        "en": "guiltily",
        "bn_syns": [],
        "en_syns": [],
        "sents": []
    },
    {
        "pron": [
            null,
            "Gullibility"
        ],
        "bn": "gullibility",
        "en": "gullibility",
        "bn_syns": [],
        "en_syns": [
            "credulousness"
        ],
        "sents": []
    },
    {
        "pron": [
            "ˈgəmˌdräp",
            "Gumdrop"
        ],
        "bn": "gumdrop",
        "en": "gumdrop",
        "bn_syns": [],
        "en_syns": [],
        "sents": [
            "If they'd used the same mechanism, called her Baby Heimlich, and had unchewed <b>gumdrops</b> or bits of brisket shoot out of her esophagus… now that would have held my attention.",
            "Go to the veterinarian's office and demand your new kitten's claws be removed and replaced with <b>gumdrops</b> ."
        ]
    },
    {
        "pron": [
            "ˌgəNG ˈhō",
            "Gung- icha"
        ],
        "bn": "gung- ইছ",
        "en": "gung-ho",
        "bn_syns": [],
        "en_syns": [],
        "sents": [
            "Apart from a tendency to be a bit <b>gung-ho</b> with the advice, I don't have the organisational skills, and smiling that much gave me a nervous tic.",
            "Now he's all <b>gung-ho</b> about getting back together with her and ‘starting a family’."
        ]
    },
    {
        "pron": [
            null,
            "Gunnysack"
        ],
        "bn": "gunnysack",
        "en": "gunnysack",
        "bn_syns": [],
        "en_syns": [
            "gunnysack",
            "burlap bag",
            "gunny sack"
        ],
        "sents": []
    },
    {
        "pron": [
            "ˈgənˌpoint",
            "Gunpoint"
        ],
        "bn": "gunpoint",
        "en": "gunpoint",
        "bn_syns": [],
        "en_syns": [
            "point"
        ],
        "sents": [
            "And when players tried to get out, they were, it is alleged, ordered back in <b>at gunpoint</b> .",
            "Three teenage boys were threatened <b>at gunpoint</b> by a youth on Wandsworth Common in two separate incidents."
        ]
    },
    {
        "pron": [
            "ˈgənˌrənər",
            "Gunrunner"
        ],
        "bn": "gunrunner",
        "en": "gunrunner",
        "bn_syns": [],
        "en_syns": [],
        "sents": [
            "Kelly draws up a large, impressive, even diverse, cast of Irish cops and <b>gunrunners</b> , Italian mobsters and mistresses, Russian immigrants and killers, saints and scoundrels.",
            "I do not think there will be a lot of terrorists and <b>gunrunners</b> , so, in general, we support that."
        ]
    },
    {
        "pron": [
            null,
            "Gunrunning"
        ],
        "bn": "gunrunning",
        "en": "gunrunning",
        "bn_syns": [],
        "en_syns": [],
        "sents": []
    },
    {
        "pron": [
            "ˈgəSHē",
            "Gushy"
        ],
        "bn": "gushy",
        "en": "gushy",
        "bn_syns": [],
        "en_syns": [
            "effusive",
            "gushing"
        ],
        "sents": [
            "It sounds all <b>gushy</b> , I know, but it was as if for the first time I could see how beautiful the world was.",
            "Rachel's vowels can make her sound <b>gushy</b> , but, in truth, she's just enthusiastic."
        ]
    },
    {
        "pron": [
            "ˈjīrəˌskōp",
            "Gyroscope"
        ],
        "bn": "gyroscope",
        "en": "gyroscope",
        "bn_syns": [
            "যে কম্পাস জাইরোস্কোপের সাহায্যে প্রকৃত উত্তর মেরুর অবস্থান এবং তার সাপেক্ষে অন্যান্য অবস্থান নির্দেশ করে"
        ],
        "en_syns": [
            "gyro"
        ],
        "sents": [
            "Each <b>gyroscope</b> 's axis, while maintaining its direction with respect to local space-time, will no longer align on the far-off star.",
            "The <b>gyroscopically</b> stabilized models, by the way, reportedly provide added compensation for movement of the boat under you."
        ]
    }
]